{
  "city_name": "Bhandardara",
  "country": "India",
  "activities": [
    {
      "activity_name": "Arthur Lake Boating & Camping",
      "category": "Relaxation",
      "duration_minutes": 180,
      "scores": {
        "budget": 4,
        "relaxed": 5,
        "adventure": 2,
        "family": 5,
        "balanced": 5
      },
      "packing_tags": [
        "sunglasses",
        "camera",
        "warm_sweater"
      ]
    },
    {
      "activity_name": "Wilson Dam Viewpoint",
      "category": "Sightseeing",
      "duration_minutes": 60,
      "scores": {
        "budget": 5,
        "relaxed": 4,
        "adventure": 1,
        "family": 5,
        "balanced": 4
      },
      "packing_tags": [
        "camera",
        "umbrella"
      ]
    },
    {
      "activity_name": "Randha Falls",
      "category": "Sightseeing",
      "duration_minutes": 90,
      "scores": {
        "budget": 5,
        "relaxed": 4,
        "adventure": 2,
        "family": 5,
        "balanced": 4
      },
      "packing_tags": [
        "camera",
        "comfortable_shoes"
      ]
    },
    {
      "activity_name": "Ratangad Fort Trek",
      "category": "Adventure",
      "duration_minutes": 300,
      "scores": {
        "budget": 4,
        "relaxed": 1,
        "adventure": 5,
        "family": 2,
        "balanced": 4
      },
      "packing_tags": [
        "hiking_boots",
        "water_bottle",
        "sunscreen",
        "flashlight"
      ]
    },
    {
      "activity_name": "Sandhan Valley Trek (Valley of Shadows)",
      "category": "Adventure",
      "duration_minutes": 360,
      "scores": {
        "budget": 4,
        "relaxed": 1,
        "adventure": 5,
        "family": 1,
        "balanced": 3
      },
      "packing_tags": [
        "hiking_boots",
        "water_shoes",
        "courage",
        "dry_bag"
      ]
    },
    {
      "activity_name": "Amruteshwar Temple",
      "category": "Culture",
      "duration_minutes": 60,
      "scores": {
        "budget": 5,
        "relaxed": 4,
        "adventure": 1,
        "family": 4,
        "balanced": 4
      },
      "packing_tags": [
        "modest_clothing",
        "camera"
      ]
    },
    {
      "activity_name": "Umbrella Falls",
      "category": "Sightseeing",
      "duration_minutes": 60,
      "scores": {
        "budget": 5,
        "relaxed": 4,
        "adventure": 2,
        "family": 5,
        "balanced": 4
      },
      "packing_tags": [
        "camera",
        "water_shoes"
      ]
    },
    {
      "activity_name": "Ghatghar Viewpoint",
      "category": "Sightseeing",
      "duration_minutes": 45,
      "scores": {
        "budget": 5,
        "relaxed": 5,
        "adventure": 1,
        "family": 4,
        "balanced": 4
      },
      "packing_tags": [
        "camera",
        "binoculars"
      ]
    },
    {
      "activity_name": "Local Maharashtrian Thali",
      "category": "Food",
      "duration_minutes": 90,
      "scores": {
        "budget": 5,
        "relaxed": 4,
        "adventure": 1,
        "family": 5,
        "balanced": 4
      },
      "packing_tags": [
        "cash",
        "hand_sanitizer"
      ]
    },
    {
      "activity_name": "Fireflies Camp (Pre-Monsoon Seasonal)",
      "category": "Adventure",
      "duration_minutes": 180,
      "scores": {
        "budget": 3,
        "relaxed": 4,
        "adventure": 4,
        "family": 5,
        "balanced": 4
      },
      "packing_tags": [
        "mosquito_repellent",
        "flashlight",
        "camera_with_tripod"
      ]
    }
  ]
}