{
  "city_name": "Bratislava",
  "country": "Slovakia",
  "activities": [
    {
      "activity_name": "Bratislava Castle Visit",
      "category": "Sightseeing",
      "duration_minutes": 120,
      "scores": {
        "budget": 4,
        "relaxed": 4,
        "adventure": 2,
        "family": 5,
        "balanced": 4
      },
      "packing_tags": [
        "walking_shoes",
        "camera",
        "water_bottle"
      ]
    },
    {
      "activity_name": "UFO Observation Deck",
      "category": "Sightseeing",
      "duration_minutes": 60,
      "scores": {
        "budget": 3,
        "relaxed": 4,
        "adventure": 2,
        "family": 4,
        "balanced": 4
      },
      "packing_tags": [
        "camera",
        "sunglasses"
      ]
    },
    {
      "activity_name": "St. Martin's Cathedral",
      "category": "Culture",
      "duration_minutes": 45,
      "scores": {
        "budget": 5,
        "relaxed": 5,
        "adventure": 1,
        "family": 4,
        "balanced": 4
      },
      "packing_tags": [
        "modest_clothing",
        "camera"
      ]
    },
    {
      "activity_name": "Danube River Cruise",
      "category": "Relaxation",
      "duration_minutes": 90,
      "scores": {
        "budget": 3,
        "relaxed": 5,
        "adventure": 1,
        "family": 5,
        "balanced": 4
      },
      "packing_tags": [
        "windbreaker",
        "sunglasses",
        "camera"
      ]
    },
    {
      "activity_name": "Traditional Bryndzove Halusky",
      "category": "Food",
      "duration_minutes": 60,
      "scores": {
        "budget": 4,
        "relaxed": 4,
        "adventure": 1,
        "family": 5,
        "balanced": 4
      },
      "packing_tags": [
        "appetite",
        "cash"
      ]
    },
    {
      "activity_name": "Blue Church Visit",
      "category": "Sightseeing",
      "duration_minutes": 30,
      "scores": {
        "budget": 5,
        "relaxed": 5,
        "adventure": 1,
        "family": 4,
        "balanced": 3
      },
      "packing_tags": [
        "camera",
        "modest_clothing"
      ]
    },
    {
      "activity_name": "Old Town Markets",
      "category": "Shopping",
      "duration_minutes": 90,
      "scores": {
        "budget": 4,
        "relaxed": 4,
        "adventure": 1,
        "family": 5,
        "balanced": 4
      },
      "packing_tags": [
        "cash",
        "tote_bag",
        "comfortable_shoes"
      ]
    },
    {
      "activity_name": "Danubiana Meulensteen Art Museum",
      "category": "Culture",
      "duration_minutes": 150,
      "scores": {
        "budget": 3,
        "relaxed": 4,
        "adventure": 1,
        "family": 4,
        "balanced": 4
      },
      "packing_tags": [
        "camera",
        "comfortable_shoes"
      ]
    },
    {
      "activity_name": "Small Carpathian Wine Route Cycling",
      "category": "Adventure",
      "duration_minutes": 240,
      "scores": {
        "budget": 3,
        "relaxed": 3,
        "adventure": 4,
        "family": 3,
        "balanced": 4
      },
      "packing_tags": [
        "sportswear",
        "water_bottle",
        "sunglasses"
      ]
    },
    {
      "activity_name": "Horsky Park Walk",
      "category": "Relaxation",
      "duration_minutes": 90,
      "scores": {
        "budget": 5,
        "relaxed": 5,
        "adventure": 2,
        "family": 5,
        "balanced": 4
      },
      "packing_tags": [
        "comfortable_shoes",
        "water_bottle"
      ]
    }
  ]
}