{
  "city_name": "Gorinchem",
  "country": "Netherlands",
  "activities": [
    {
      "activity_name": "Gorinchem City Walls Walk",
      "category": "Sightseeing",
      "duration_minutes": 90,
      "scores": {
        "budget": 5,
        "relaxed": 4,
        "adventure": 2,
        "family": 5,
        "balanced": 4
      },
      "packing_tags": [
        "walking_shoes",
        "camera"
      ]
    },
    {
      "activity_name": "Gorcums Museum",
      "category": "Culture",
      "duration_minutes": 90,
      "scores": {
        "budget": 4,
        "relaxed": 4,
        "adventure": 1,
        "family": 4,
        "balanced": 4
      },
      "packing_tags": [
        "audio_guide"
      ]
    },
    {
      "activity_name": "Linge River Boat Tour",
      "category": "Relaxation",
      "duration_minutes": 120,
      "scores": {
        "budget": 3,
        "relaxed": 5,
        "adventure": 1,
        "family": 5,
        "balanced": 4
      },
      "packing_tags": [
        "windbreaker",
        "sunglasses"
      ]
    },
    {
      "activity_name": "Dalempoort Gate View",
      "category": "Sightseeing",
      "duration_minutes": 30,
      "scores": {
        "budget": 5,
        "relaxed": 5,
        "adventure": 1,
        "family": 5,
        "balanced": 4
      },
      "packing_tags": [
        "camera_lens"
      ]
    },
    {
      "activity_name": "Piazza Center Shopping",
      "category": "Shopping",
      "duration_minutes": 120,
      "scores": {
        "budget": 3,
        "relaxed": 4,
        "adventure": 1,
        "family": 4,
        "balanced": 3
      },
      "packing_tags": [
        "wallet",
        "shopping_bags"
      ]
    },
    {
      "activity_name": "Buiten de Waterpoort Park",
      "category": "Relaxation",
      "duration_minutes": 90,
      "scores": {
        "budget": 5,
        "relaxed": 5,
        "adventure": 1,
        "family": 5,
        "balanced": 4
      },
      "packing_tags": [
        "picnic_blanket",
        "snacks"
      ]
    },
    {
      "activity_name": "Hendrick Hamel Museum",
      "category": "Culture",
      "duration_minutes": 60,
      "scores": {
        "budget": 4,
        "relaxed": 4,
        "adventure": 1,
        "family": 4,
        "balanced": 4
      },
      "packing_tags": [
        "notebook"
      ]
    },
    {
      "activity_name": "Grote Kerk Tower Climb",
      "category": "Adventure",
      "duration_minutes": 60,
      "scores": {
        "budget": 4,
        "relaxed": 2,
        "adventure": 4,
        "family": 4,
        "balanced": 4
      },
      "packing_tags": [
        "sneakers",
        "water_bottle"
      ]
    },
    {
      "activity_name": "Vismarkt Square Dining",
      "category": "Food",
      "duration_minutes": 90,
      "scores": {
        "budget": 3,
        "relaxed": 5,
        "adventure": 1,
        "family": 5,
        "balanced": 4
      },
      "packing_tags": [
        "hand_sanitizer"
      ]
    },
    {
      "activity_name": "Merwede River Beach",
      "category": "Relaxation",
      "duration_minutes": 120,
      "scores": {
        "budget": 5,
        "relaxed": 5,
        "adventure": 2,
        "family": 5,
        "balanced": 4
      },
      "packing_tags": [
        "swimwear",
        "beach_towel"
      ]
    }
  ]
}