{
  "city_name": "Interlaken",
  "country": "Switzerland",
  "activities": [
    {
      "activity_name": "Harder Kulm Funicular & View",
      "category": "Sightseeing",
      "duration_minutes": 120,
      "scores": {
        "budget": 3,
        "relaxed": 4,
        "adventure": 2,
        "family": 5,
        "balanced": 5
      },
      "packing_tags": [
        "camera",
        "light_jacket"
      ]
    },
    {
      "activity_name": "Lake Thun Paddle Steamer Cruise",
      "category": "Relaxation",
      "duration_minutes": 180,
      "scores": {
        "budget": 3,
        "relaxed": 5,
        "adventure": 1,
        "family": 5,
        "balanced": 5
      },
      "packing_tags": [
        "sunglasses",
        "camera",
        "windbreaker"
      ]
    },
    {
      "activity_name": "Lake Brienz Turquoise Waters Tour",
      "category": "Sightseeing",
      "duration_minutes": 120,
      "scores": {
        "budget": 3,
        "relaxed": 5,
        "adventure": 1,
        "family": 5,
        "balanced": 4
      },
      "packing_tags": [
        "camera",
        "sunscreen"
      ]
    },
    {
      "activity_name": "Jungfraujoch (Top of Europe) Trip",
      "category": "Adventure",
      "duration_minutes": 480,
      "scores": {
        "budget": 1,
        "relaxed": 3,
        "adventure": 5,
        "family": 5,
        "balanced": 4
      },
      "packing_tags": [
        "heavy_jacket",
        "sunglasses",
        "snow_boots",
        "altitude_medication"
      ]
    },
    {
      "activity_name": "Schynige Platte Alpine Garden",
      "category": "Sightseeing",
      "duration_minutes": 240,
      "scores": {
        "budget": 3,
        "relaxed": 4,
        "adventure": 3,
        "family": 4,
        "balanced": 4
      },
      "packing_tags": [
        "hiking_shoes",
        "camera",
        "sunscreen"
      ]
    },
    {
      "activity_name": "H\u00f6he Matte Park Paraglider Watching",
      "category": "Relaxation",
      "duration_minutes": 60,
      "scores": {
        "budget": 5,
        "relaxed": 5,
        "adventure": 1,
        "family": 5,
        "balanced": 4
      },
      "packing_tags": [
        "picnic_blanket",
        "camera"
      ]
    },
    {
      "activity_name": "Tandem Paragliding Experience",
      "category": "Adventure",
      "duration_minutes": 90,
      "scores": {
        "budget": 1,
        "relaxed": 1,
        "adventure": 5,
        "family": 2,
        "balanced": 3
      },
      "packing_tags": [
        "closed_toe_shoes",
        "windbreaker",
        "courage"
      ]
    },
    {
      "activity_name": "St. Beatus Caves Exploration",
      "category": "Adventure",
      "duration_minutes": 150,
      "scores": {
        "budget": 3,
        "relaxed": 3,
        "adventure": 4,
        "family": 5,
        "balanced": 4
      },
      "packing_tags": [
        "comfortable_shoes",
        "warm_layer"
      ]
    },
    {
      "activity_name": "Aare River Walk",
      "category": "Relaxation",
      "duration_minutes": 60,
      "scores": {
        "budget": 5,
        "relaxed": 5,
        "adventure": 1,
        "family": 5,
        "balanced": 4
      },
      "packing_tags": [
        "walking_shoes"
      ]
    },
    {
      "activity_name": "Traditional Swiss Fondue Dinner",
      "category": "Food",
      "duration_minutes": 120,
      "scores": {
        "budget": 2,
        "relaxed": 5,
        "adventure": 1,
        "family": 5,
        "balanced": 4
      },
      "packing_tags": [
        "appetite",
        "credit_card"
      ]
    }
  ]
}