{
  "city_name": "Interlaken",
  "country": "Switzerland",
  "activities": [
    {
      "activity_name": "Harder Kulm Funicular",
      "category": "Sightseeing",
      "duration_minutes": 120,
      "scores": {
        "budget": 3,
        "relaxed": 4,
        "adventure": 3,
        "family": 5,
        "balanced": 4
      },
      "packing_tags": [
        "camera",
        "warm_jacket",
        "sunglasses"
      ]
    },
    {
      "activity_name": "Jungfraujoch Excursion",
      "category": "Adventure",
      "duration_minutes": 480,
      "scores": {
        "budget": 1,
        "relaxed": 3,
        "adventure": 5,
        "family": 5,
        "balanced": 4
      },
      "packing_tags": [
        "winter_clothing",
        "sunglasses",
        "camera"
      ]
    },
    {
      "activity_name": "Tandem Paragliding",
      "category": "Adventure",
      "duration_minutes": 90,
      "scores": {
        "budget": 1,
        "relaxed": 1,
        "adventure": 5,
        "family": 2,
        "balanced": 3
      },
      "packing_tags": [
        "windbreaker",
        "sunglasses",
        "courage"
      ]
    },
    {
      "activity_name": "Lake Thun Cruise",
      "category": "Relaxation",
      "duration_minutes": 150,
      "scores": {
        "budget": 3,
        "relaxed": 5,
        "adventure": 1,
        "family": 5,
        "balanced": 5
      },
      "packing_tags": [
        "camera",
        "sun_hat",
        "windbreaker"
      ]
    },
    {
      "activity_name": "Lake Brienz Cruise",
      "category": "Relaxation",
      "duration_minutes": 150,
      "scores": {
        "budget": 3,
        "relaxed": 5,
        "adventure": 1,
        "family": 5,
        "balanced": 5
      },
      "packing_tags": [
        "camera",
        "sunglasses",
        "light_jacket"
      ]
    },
    {
      "activity_name": "Hohematte Park",
      "category": "Relaxation",
      "duration_minutes": 60,
      "scores": {
        "budget": 5,
        "relaxed": 5,
        "adventure": 1,
        "family": 5,
        "balanced": 4
      },
      "packing_tags": [
        "picnic_blanket",
        "camera",
        "comfortable_shoes"
      ]
    },
    {
      "activity_name": "St. Beatus Caves",
      "category": "Sightseeing",
      "duration_minutes": 120,
      "scores": {
        "budget": 3,
        "relaxed": 3,
        "adventure": 3,
        "family": 5,
        "balanced": 4
      },
      "packing_tags": [
        "comfortable_shoes",
        "light_jacket",
        "camera"
      ]
    },
    {
      "activity_name": "Schynige Platte Railway",
      "category": "Sightseeing",
      "duration_minutes": 240,
      "scores": {
        "budget": 2,
        "relaxed": 4,
        "adventure": 2,
        "family": 5,
        "balanced": 4
      },
      "packing_tags": [
        "camera",
        "sun_hat",
        "walking_shoes"
      ]
    },
    {
      "activity_name": "Swiss Chocolate Making",
      "category": "Food",
      "duration_minutes": 90,
      "scores": {
        "budget": 3,
        "relaxed": 4,
        "adventure": 1,
        "family": 5,
        "balanced": 4
      },
      "packing_tags": [
        "sweet_tooth",
        "camera",
        "apron"
      ]
    },
    {
      "activity_name": "Staubbach Falls Trip",
      "category": "Sightseeing",
      "duration_minutes": 180,
      "scores": {
        "budget": 4,
        "relaxed": 4,
        "adventure": 3,
        "family": 5,
        "balanced": 4
      },
      "packing_tags": [
        "camera",
        "rain_jacket",
        "walking_shoes"
      ]
    }
  ]
}