{
  "city_name": "Jaisalmer",
  "country": "India",
  "activities": [
    {
      "activity_name": "Jaisalmer Fort (Sonar Quila) Tour",
      "category": "Culture",
      "duration_minutes": 180,
      "scores": {
        "budget": 4,
        "relaxed": 3,
        "adventure": 2,
        "family": 5,
        "balanced": 5
      },
      "packing_tags": [
        "comfortable_shoes",
        "sunglasses",
        "water_bottle",
        "camera"
      ]
    },
    {
      "activity_name": "Sam Sand Dunes Desert Safari",
      "category": "Adventure",
      "duration_minutes": 360,
      "scores": {
        "budget": 2,
        "relaxed": 2,
        "adventure": 5,
        "family": 5,
        "balanced": 5
      },
      "packing_tags": [
        "sunscreen",
        "sunglasses",
        "scarf",
        "light_jacket"
      ]
    },
    {
      "activity_name": "Patwon Ki Haveli",
      "category": "Culture",
      "duration_minutes": 90,
      "scores": {
        "budget": 4,
        "relaxed": 4,
        "adventure": 1,
        "family": 4,
        "balanced": 4
      },
      "packing_tags": [
        "camera",
        "comfortable_shoes"
      ]
    },
    {
      "activity_name": "Gadisar Lake Boating",
      "category": "Relaxation",
      "duration_minutes": 90,
      "scores": {
        "budget": 4,
        "relaxed": 5,
        "adventure": 1,
        "family": 5,
        "balanced": 4
      },
      "packing_tags": [
        "camera",
        "sunglasses"
      ]
    },
    {
      "activity_name": "Desert Camping & Kalbelia Dance",
      "category": "Culture",
      "duration_minutes": 480,
      "scores": {
        "budget": 2,
        "relaxed": 4,
        "adventure": 3,
        "family": 5,
        "balanced": 4
      },
      "packing_tags": [
        "warm_sweater",
        "camera",
        "flashlight"
      ]
    },
    {
      "activity_name": "Bada Bagh Cenotaphs Sunset",
      "category": "Sightseeing",
      "duration_minutes": 90,
      "scores": {
        "budget": 4,
        "relaxed": 4,
        "adventure": 1,
        "family": 4,
        "balanced": 4
      },
      "packing_tags": [
        "camera",
        "light_jacket"
      ]
    },
    {
      "activity_name": "Kuldhara Abandoned Village Visit",
      "category": "Sightseeing",
      "duration_minutes": 120,
      "scores": {
        "budget": 4,
        "relaxed": 3,
        "adventure": 3,
        "family": 4,
        "balanced": 4
      },
      "packing_tags": [
        "camera",
        "sunscreen",
        "water_bottle"
      ]
    },
    {
      "activity_name": "Jain Temples Walk",
      "category": "Culture",
      "duration_minutes": 90,
      "scores": {
        "budget": 4,
        "relaxed": 4,
        "adventure": 1,
        "family": 4,
        "balanced": 4
      },
      "packing_tags": [
        "modest_clothing",
        "slip_on_shoes"
      ]
    },
    {
      "activity_name": "Thar Heritage Museum",
      "category": "Culture",
      "duration_minutes": 60,
      "scores": {
        "budget": 5,
        "relaxed": 4,
        "adventure": 1,
        "family": 3,
        "balanced": 3
      },
      "packing_tags": [
        "glasses"
      ]
    },
    {
      "activity_name": "Sadar Bazaar Leather Shopping",
      "category": "Shopping",
      "duration_minutes": 120,
      "scores": {
        "budget": 3,
        "relaxed": 3,
        "adventure": 1,
        "family": 4,
        "balanced": 3
      },
      "packing_tags": [
        "cash",
        "tote_bag",
        "negotiation_skills"
      ]
    }
  ]
}