{
  "city_name": "Karjat",
  "country": "India",
  "activities": [
    {
      "activity_name": "Kondana Caves Trek",
      "category": "Adventure",
      "duration_minutes": 180,
      "scores": {
        "budget": 5,
        "relaxed": 3,
        "adventure": 4,
        "family": 4,
        "balanced": 4
      },
      "packing_tags": [
        "hiking_shoes",
        "water_bottle",
        "camera"
      ]
    },
    {
      "activity_name": "Ulhas Valley Exploration",
      "category": "Sightseeing",
      "duration_minutes": 150,
      "scores": {
        "budget": 5,
        "relaxed": 4,
        "adventure": 3,
        "family": 4,
        "balanced": 4
      },
      "packing_tags": [
        "comfortable_shoes",
        "binoculars"
      ]
    },
    {
      "activity_name": "Kothaligad (Peth) Fort Trek",
      "category": "Adventure",
      "duration_minutes": 240,
      "scores": {
        "budget": 5,
        "relaxed": 2,
        "adventure": 5,
        "family": 3,
        "balanced": 4
      },
      "packing_tags": [
        "hiking_boots",
        "water_bottle",
        "sunscreen",
        "hat"
      ]
    },
    {
      "activity_name": "Bhivpuri Waterfall Visit",
      "category": "Sightseeing",
      "duration_minutes": 120,
      "scores": {
        "budget": 5,
        "relaxed": 4,
        "adventure": 3,
        "family": 4,
        "balanced": 4
      },
      "packing_tags": [
        "water_shoes",
        "towel",
        "camera"
      ]
    },
    {
      "activity_name": "Morbe Dam Sunset",
      "category": "Relaxation",
      "duration_minutes": 90,
      "scores": {
        "budget": 5,
        "relaxed": 5,
        "adventure": 1,
        "family": 5,
        "balanced": 4
      },
      "packing_tags": [
        "camera",
        "sunglasses"
      ]
    },
    {
      "activity_name": "ND Studios Theme Park",
      "category": "Sightseeing",
      "duration_minutes": 240,
      "scores": {
        "budget": 2,
        "relaxed": 4,
        "adventure": 2,
        "family": 5,
        "balanced": 4
      },
      "packing_tags": [
        "comfortable_shoes",
        "camera",
        "hat"
      ]
    },
    {
      "activity_name": "Bahiri Cave Trek",
      "category": "Adventure",
      "duration_minutes": 300,
      "scores": {
        "budget": 5,
        "relaxed": 1,
        "adventure": 5,
        "family": 1,
        "balanced": 3
      },
      "packing_tags": [
        "hiking_boots",
        "courage",
        "water_bottle"
      ]
    },
    {
      "activity_name": "Blackwaters of Pali Bhutivali Dam",
      "category": "Relaxation",
      "duration_minutes": 120,
      "scores": {
        "budget": 5,
        "relaxed": 5,
        "adventure": 2,
        "family": 4,
        "balanced": 4
      },
      "packing_tags": [
        "camera",
        "picnic_blanket"
      ]
    },
    {
      "activity_name": "Saltt Restaurant Farmhouse Dining",
      "category": "Food",
      "duration_minutes": 120,
      "scores": {
        "budget": 2,
        "relaxed": 5,
        "adventure": 1,
        "family": 5,
        "balanced": 4
      },
      "packing_tags": [
        "smart_casual_outfit",
        "credit_card"
      ]
    },
    {
      "activity_name": "Sondai Fort Sunrise Trek",
      "category": "Adventure",
      "duration_minutes": 180,
      "scores": {
        "budget": 5,
        "relaxed": 2,
        "adventure": 4,
        "family": 3,
        "balanced": 4
      },
      "packing_tags": [
        "flashlight",
        "hiking_shoes",
        "water_bottle"
      ]
    }
  ]
}