{
  "city_name": "Kolad",
  "country": "India",
  "activities": [
    {
      "activity_name": "Kundalika River White Water Rafting",
      "category": "Adventure",
      "duration_minutes": 180,
      "scores": {
        "budget": 2,
        "relaxed": 1,
        "adventure": 5,
        "family": 3,
        "balanced": 4
      },
      "packing_tags": [
        "swimwear",
        "water_shoes",
        "towel",
        "sunscreen"
      ]
    },
    {
      "activity_name": "Devkund Waterfall Trek",
      "category": "Adventure",
      "duration_minutes": 300,
      "scores": {
        "budget": 4,
        "relaxed": 2,
        "adventure": 5,
        "family": 3,
        "balanced": 4
      },
      "packing_tags": [
        "hiking_shoes",
        "water_bottle",
        "swimwear",
        "camera"
      ]
    },
    {
      "activity_name": "Tamhini Ghat Scenic Drive",
      "category": "Sightseeing",
      "duration_minutes": 120,
      "scores": {
        "budget": 4,
        "relaxed": 5,
        "adventure": 2,
        "family": 5,
        "balanced": 5
      },
      "packing_tags": [
        "camera",
        "windbreaker",
        "sunglasses"
      ]
    },
    {
      "activity_name": "Kuda Caves Exploration",
      "category": "Culture",
      "duration_minutes": 90,
      "scores": {
        "budget": 5,
        "relaxed": 4,
        "adventure": 2,
        "family": 4,
        "balanced": 4
      },
      "packing_tags": [
        "comfortable_shoes",
        "flashlight"
      ]
    },
    {
      "activity_name": "Bhira Dam Picnic",
      "category": "Relaxation",
      "duration_minutes": 120,
      "scores": {
        "budget": 5,
        "relaxed": 5,
        "adventure": 1,
        "family": 5,
        "balanced": 4
      },
      "packing_tags": [
        "picnic_blanket",
        "camera",
        "sunglasses"
      ]
    },
    {
      "activity_name": "Plus Valley Trek",
      "category": "Adventure",
      "duration_minutes": 240,
      "scores": {
        "budget": 5,
        "relaxed": 2,
        "adventure": 5,
        "family": 2,
        "balanced": 3
      },
      "packing_tags": [
        "hiking_boots",
        "water_bottle",
        "energy_bars"
      ]
    },
    {
      "activity_name": "Ghosalgad Fort Hike",
      "category": "Adventure",
      "duration_minutes": 150,
      "scores": {
        "budget": 5,
        "relaxed": 3,
        "adventure": 4,
        "family": 3,
        "balanced": 4
      },
      "packing_tags": [
        "hiking_shoes",
        "hat",
        "sunscreen"
      ]
    },
    {
      "activity_name": "Sutarwadi Lake Walk",
      "category": "Relaxation",
      "duration_minutes": 60,
      "scores": {
        "budget": 5,
        "relaxed": 5,
        "adventure": 1,
        "family": 5,
        "balanced": 4
      },
      "packing_tags": [
        "camera",
        "mosquito_repellent"
      ]
    },
    {
      "activity_name": "Riverside Camping & Bonfire",
      "category": "Relaxation",
      "duration_minutes": 480,
      "scores": {
        "budget": 3,
        "relaxed": 4,
        "adventure": 3,
        "family": 4,
        "balanced": 4
      },
      "packing_tags": [
        "warm_sweater",
        "flashlight",
        "mosquito_repellent"
      ]
    },
    {
      "activity_name": "Kolad Zipline & Kayaking",
      "category": "Adventure",
      "duration_minutes": 120,
      "scores": {
        "budget": 3,
        "relaxed": 2,
        "adventure": 4,
        "family": 4,
        "balanced": 4
      },
      "packing_tags": [
        "sportswear",
        "water_shoes",
        "sunscreen"
      ]
    }
  ]
}