{
  "city_name": "Nijmegen",
  "country": "Netherlands",
  "activities": [
    {
      "activity_name": "Valkhof Park Exploration",
      "category": "Relaxation",
      "duration_minutes": 90,
      "scores": {
        "budget": 5,
        "relaxed": 5,
        "adventure": 1,
        "family": 5,
        "balanced": 4
      },
      "packing_tags": [
        "walking_shoes",
        "camera"
      ]
    },
    {
      "activity_name": "Grote Markt Walk",
      "category": "Sightseeing",
      "duration_minutes": 60,
      "scores": {
        "budget": 5,
        "relaxed": 5,
        "adventure": 1,
        "family": 5,
        "balanced": 4
      },
      "packing_tags": [
        "sunglasses"
      ]
    },
    {
      "activity_name": "MuZIEum Experience",
      "category": "Culture",
      "duration_minutes": 120,
      "scores": {
        "budget": 3,
        "relaxed": 3,
        "adventure": 3,
        "family": 4,
        "balanced": 4
      },
      "packing_tags": [
        "comfortable_clothing"
      ]
    },
    {
      "activity_name": "St. Stephen's Church",
      "category": "Culture",
      "duration_minutes": 60,
      "scores": {
        "budget": 4,
        "relaxed": 4,
        "adventure": 1,
        "family": 4,
        "balanced": 4
      },
      "packing_tags": [
        "modest_clothing",
        "camera"
      ]
    },
    {
      "activity_name": "Kronenburgerpark Picnic",
      "category": "Relaxation",
      "duration_minutes": 90,
      "scores": {
        "budget": 5,
        "relaxed": 5,
        "adventure": 1,
        "family": 5,
        "balanced": 4
      },
      "packing_tags": [
        "picnic_blanket"
      ]
    },
    {
      "activity_name": "Waalbrug Bridge Walk",
      "category": "Adventure",
      "duration_minutes": 60,
      "scores": {
        "budget": 5,
        "relaxed": 4,
        "adventure": 2,
        "family": 4,
        "balanced": 4
      },
      "packing_tags": [
        "windbreaker",
        "camera_lens"
      ]
    },
    {
      "activity_name": "Lange Hezelstraat Boutiques",
      "category": "Shopping",
      "duration_minutes": 120,
      "scores": {
        "budget": 2,
        "relaxed": 4,
        "adventure": 1,
        "family": 4,
        "balanced": 3
      },
      "packing_tags": [
        "credit_card",
        "shopping_bags"
      ]
    },
    {
      "activity_name": "Honigcomplex Food Market",
      "category": "Food",
      "duration_minutes": 90,
      "scores": {
        "budget": 3,
        "relaxed": 4,
        "adventure": 1,
        "family": 4,
        "balanced": 4
      },
      "packing_tags": [
        "hand_sanitizer"
      ]
    },
    {
      "activity_name": "National Liberation Museum",
      "category": "Culture",
      "duration_minutes": 150,
      "scores": {
        "budget": 3,
        "relaxed": 3,
        "adventure": 1,
        "family": 4,
        "balanced": 4
      },
      "packing_tags": [
        "notebook",
        "reading_glasses"
      ]
    },
    {
      "activity_name": "Ooijpolder Nature Hike",
      "category": "Adventure",
      "duration_minutes": 180,
      "scores": {
        "budget": 5,
        "relaxed": 3,
        "adventure": 4,
        "family": 4,
        "balanced": 4
      },
      "packing_tags": [
        "hiking_boots",
        "water_bottle",
        "binoculars"
      ]
    }
  ]
}