{
  "city_name": "Rome",
  "country": "Italy",
  "activities": [
    {
      "activity_name": "Colosseum & Roman Forum",
      "category": "Culture",
      "duration_minutes": 240,
      "scores": {
        "budget": 3,
        "relaxed": 2,
        "adventure": 2,
        "family": 5,
        "balanced": 5
      },
      "packing_tags": [
        "comfortable_shoes",
        "sunscreen",
        "water_bottle",
        "advance_tickets"
      ]
    },
    {
      "activity_name": "Vatican Museums & Sistine Chapel",
      "category": "Culture",
      "duration_minutes": 240,
      "scores": {
        "budget": 2,
        "relaxed": 2,
        "adventure": 1,
        "family": 4,
        "balanced": 5
      },
      "packing_tags": [
        "modest_clothing",
        "comfortable_shoes",
        "advance_tickets"
      ]
    },
    {
      "activity_name": "Trevi Fountain Coin Toss",
      "category": "Sightseeing",
      "duration_minutes": 45,
      "scores": {
        "budget": 5,
        "relaxed": 4,
        "adventure": 1,
        "family": 5,
        "balanced": 4
      },
      "packing_tags": [
        "camera",
        "cash",
        "anti_theft_bag"
      ]
    },
    {
      "activity_name": "Pantheon Architecture",
      "category": "Culture",
      "duration_minutes": 60,
      "scores": {
        "budget": 5,
        "relaxed": 4,
        "adventure": 1,
        "family": 5,
        "balanced": 4
      },
      "packing_tags": [
        "camera",
        "modest_clothing"
      ]
    },
    {
      "activity_name": "Piazza Navona Evening Walk",
      "category": "Relaxation",
      "duration_minutes": 90,
      "scores": {
        "budget": 5,
        "relaxed": 5,
        "adventure": 1,
        "family": 5,
        "balanced": 4
      },
      "packing_tags": [
        "camera",
        "light_jacket"
      ]
    },
    {
      "activity_name": "Spanish Steps Stroll",
      "category": "Sightseeing",
      "duration_minutes": 45,
      "scores": {
        "budget": 5,
        "relaxed": 4,
        "adventure": 1,
        "family": 4,
        "balanced": 3
      },
      "packing_tags": [
        "camera",
        "sunglasses"
      ]
    },
    {
      "activity_name": "Trastevere Authentic Italian Dining",
      "category": "Food",
      "duration_minutes": 150,
      "scores": {
        "budget": 3,
        "relaxed": 5,
        "adventure": 1,
        "family": 4,
        "balanced": 5
      },
      "packing_tags": [
        "appetite",
        "casual_wear",
        "cash"
      ]
    },
    {
      "activity_name": "Villa Borghese Gardens Picnic",
      "category": "Relaxation",
      "duration_minutes": 150,
      "scores": {
        "budget": 4,
        "relaxed": 5,
        "adventure": 2,
        "family": 5,
        "balanced": 4
      },
      "packing_tags": [
        "picnic_blanket",
        "camera",
        "comfortable_shoes"
      ]
    },
    {
      "activity_name": "Authentic Gelato Tasting",
      "category": "Food",
      "duration_minutes": 30,
      "scores": {
        "budget": 4,
        "relaxed": 5,
        "adventure": 1,
        "family": 5,
        "balanced": 4
      },
      "packing_tags": [
        "cash",
        "sweet_tooth"
      ]
    },
    {
      "activity_name": "Castel Sant'Angelo Tour",
      "category": "Culture",
      "duration_minutes": 120,
      "scores": {
        "budget": 3,
        "relaxed": 4,
        "adventure": 2,
        "family": 4,
        "balanced": 4
      },
      "packing_tags": [
        "camera",
        "comfortable_shoes"
      ]
    }
  ]
}