{
  "city_name": "Thrissur",
  "country": "India",
  "activities": [
    {
      "activity_name": "Vadakkunnathan Temple",
      "category": "Culture",
      "duration_minutes": 90,
      "scores": {
        "budget": 5,
        "relaxed": 4,
        "adventure": 1,
        "family": 4,
        "balanced": 4
      },
      "packing_tags": [
        "modest_clothing",
        "slip_on_shoes"
      ]
    },
    {
      "activity_name": "Athirappilly Waterfalls Trek",
      "category": "Adventure",
      "duration_minutes": 180,
      "scores": {
        "budget": 4,
        "relaxed": 2,
        "adventure": 5,
        "family": 4,
        "balanced": 4
      },
      "packing_tags": [
        "hiking_shoes",
        "waterproof_camera",
        "mosquito_repellent"
      ]
    },
    {
      "activity_name": "Thrissur Zoo and Museum",
      "category": "Sightseeing",
      "duration_minutes": 120,
      "scores": {
        "budget": 4,
        "relaxed": 4,
        "adventure": 2,
        "family": 5,
        "balanced": 4
      },
      "packing_tags": [
        "sunscreen",
        "water_bottle",
        "stroller"
      ]
    },
    {
      "activity_name": "Shakthan Thampuran Palace",
      "category": "Culture",
      "duration_minutes": 90,
      "scores": {
        "budget": 4,
        "relaxed": 4,
        "adventure": 1,
        "family": 4,
        "balanced": 4
      },
      "packing_tags": [
        "camera",
        "notebook"
      ]
    },
    {
      "activity_name": "Vilangan Hills Viewpoint",
      "category": "Relaxation",
      "duration_minutes": 90,
      "scores": {
        "budget": 5,
        "relaxed": 5,
        "adventure": 2,
        "family": 5,
        "balanced": 4
      },
      "packing_tags": [
        "sunglasses",
        "picnic_blanket"
      ]
    },
    {
      "activity_name": "Basilica of Our Lady of Dolours",
      "category": "Culture",
      "duration_minutes": 60,
      "scores": {
        "budget": 5,
        "relaxed": 5,
        "adventure": 1,
        "family": 4,
        "balanced": 4
      },
      "packing_tags": [
        "modest_clothing"
      ]
    },
    {
      "activity_name": "Kerala Kalamandalam Tour",
      "category": "Culture",
      "duration_minutes": 150,
      "scores": {
        "budget": 3,
        "relaxed": 4,
        "adventure": 1,
        "family": 4,
        "balanced": 4
      },
      "packing_tags": [
        "camera",
        "respectful_attire"
      ]
    },
    {
      "activity_name": "Traditional Kerala Sadhya",
      "category": "Food",
      "duration_minutes": 90,
      "scores": {
        "budget": 4,
        "relaxed": 4,
        "adventure": 2,
        "family": 5,
        "balanced": 4
      },
      "packing_tags": [
        "hand_sanitizer"
      ]
    },
    {
      "activity_name": "Silk and Gold Shopping",
      "category": "Shopping",
      "duration_minutes": 180,
      "scores": {
        "budget": 1,
        "relaxed": 4,
        "adventure": 1,
        "family": 4,
        "balanced": 3
      },
      "packing_tags": [
        "credit_card",
        "shopping_bags"
      ]
    },
    {
      "activity_name": "Snehatheeram Beach Sunset",
      "category": "Relaxation",
      "duration_minutes": 90,
      "scores": {
        "budget": 5,
        "relaxed": 5,
        "adventure": 1,
        "family": 5,
        "balanced": 4
      },
      "packing_tags": [
        "beach_mat",
        "camera"
      ]
    }
  ]
}