{
  "city_name": "Walong",
  "country": "India",
  "activities": [
    {
      "activity_name": "Walong War Memorial",
      "category": "Culture",
      "duration_minutes": 60,
      "scores": {
        "budget": 5,
        "relaxed": 4,
        "adventure": 1,
        "family": 5,
        "balanced": 4
      },
      "packing_tags": [
        "camera",
        "respectful_attire"
      ]
    },
    {
      "activity_name": "Namti Plains Battlefield",
      "category": "Culture",
      "duration_minutes": 90,
      "scores": {
        "budget": 5,
        "relaxed": 4,
        "adventure": 2,
        "family": 4,
        "balanced": 4
      },
      "packing_tags": [
        "walking_shoes",
        "camera"
      ]
    },
    {
      "activity_name": "Dong Sunrise Point Trek",
      "category": "Adventure",
      "duration_minutes": 360,
      "scores": {
        "budget": 4,
        "relaxed": 1,
        "adventure": 5,
        "family": 3,
        "balanced": 4
      },
      "packing_tags": [
        "warm_jacket",
        "flashlight",
        "water_bottle"
      ]
    },
    {
      "activity_name": "Helmet Top Viewpoint",
      "category": "Sightseeing",
      "duration_minutes": 120,
      "scores": {
        "budget": 4,
        "relaxed": 4,
        "adventure": 3,
        "family": 5,
        "balanced": 4
      },
      "packing_tags": [
        "camera",
        "binoculars",
        "windbreaker"
      ]
    },
    {
      "activity_name": "Lohit River Bank Walk",
      "category": "Relaxation",
      "duration_minutes": 60,
      "scores": {
        "budget": 5,
        "relaxed": 5,
        "adventure": 1,
        "family": 5,
        "balanced": 4
      },
      "packing_tags": [
        "comfortable_shoes",
        "camera"
      ]
    },
    {
      "activity_name": "Kibithu Border Visit",
      "category": "Sightseeing",
      "duration_minutes": 180,
      "scores": {
        "budget": 3,
        "relaxed": 4,
        "adventure": 3,
        "family": 5,
        "balanced": 4
      },
      "packing_tags": [
        "id_card",
        "camera",
        "sunglasses"
      ]
    },
    {
      "activity_name": "Hot Springs Bath",
      "category": "Relaxation",
      "duration_minutes": 90,
      "scores": {
        "budget": 4,
        "relaxed": 5,
        "adventure": 1,
        "family": 5,
        "balanced": 4
      },
      "packing_tags": [
        "swimwear",
        "towel",
        "change_of_clothes"
      ]
    },
    {
      "activity_name": "Local Meyor Tribe Food",
      "category": "Food",
      "duration_minutes": 60,
      "scores": {
        "budget": 4,
        "relaxed": 5,
        "adventure": 1,
        "family": 5,
        "balanced": 4
      },
      "packing_tags": [
        "appetite",
        "cash"
      ]
    },
    {
      "activity_name": "Walong Suspension Bridge",
      "category": "Adventure",
      "duration_minutes": 45,
      "scores": {
        "budget": 5,
        "relaxed": 3,
        "adventure": 4,
        "family": 4,
        "balanced": 4
      },
      "packing_tags": [
        "camera",
        "courage",
        "comfortable_shoes"
      ]
    },
    {
      "activity_name": "Pine Forest Trek",
      "category": "Adventure",
      "duration_minutes": 180,
      "scores": {
        "budget": 5,
        "relaxed": 2,
        "adventure": 5,
        "family": 3,
        "balanced": 4
      },
      "packing_tags": [
        "hiking_boots",
        "water_bottle",
        "sunscreen"
      ]
    }
  ]
}